prom2csv/__init__.py
prom2csv/prom2csv.py
prom2csv-0.9.1.dist-info/METADATA
prom2csv-0.9.1.dist-info/WHEEL
prom2csv-0.9.1.dist-info/entry_points.txt
prom2csv-0.9.1.dist-info/licenses/LICENSE
prom2csv-0.9.1.dist-info/RECORD
